wikiextractor/WikiExtractor.py
wikiextractor/__init__.py
wikiextractor/cirrus-extract.py
wikiextractor/clean.py
wikiextractor/extract.py
wikiextractor/extractPage.py
wikiextractor-3.0.4.dist-info/LICENSE
wikiextractor-3.0.4.dist-info/METADATA
wikiextractor-3.0.4.dist-info/WHEEL
wikiextractor-3.0.4.dist-info/entry_points.txt
wikiextractor-3.0.4.dist-info/top_level.txt
wikiextractor-3.0.4.dist-info/RECORD
