Metadata-Version: 2.1
Name: wikiextractor
Version: 3.0.4
Summary: A tool for extracting plain text from Wikipedia dumps
Home-page: https://github.com/attardi/wikiextractor
Author: Giuseppe Attardi
Author-email: attardi@gmail.com
License: GNU Affero General Public License
Platform: UNKNOWN
Classifier: Development Status :: 5 - Production/Stable
Classifier: Intended Audience :: Developers
Classifier: Topic :: Text Processing :: Linguistic
Classifier: License :: OSI Approved :: GNU Affero General Public License v3 or later (AGPLv3+)
Classifier: Programming Language :: Python :: 3
Requires-Python: >=3.6
